{
  "roast_text": "\n\ud83d\udd25 RESUME ROAST REPORT \ud83d\udd25\n\u2501\u2501\u2501\u2501\u2501\u2501\u2501\u2501\u2501\u2501\u2501\u2501\u2501\u2501\u2501\u2501\u2501\u2501\u2501\u2501\u2501\u2501\u2501\u2501\u2501\u2501\u2501\u2501\u2501\u2501\u2501\u2501\u2501\u2501\u2501\u2501\n\n\ud83d\udcca OVERALL SCORE: 88/100 \ud83d\udc4d Pretty good!\n\u2501\u2501\u2501\u2501\u2501\u2501\u2501\u2501\u2501\u2501\u2501\u2501\u2501\u2501\u2501\u2501\u2501\u2501\u2501\u2501\u2501\u2501\u2501\u2501\u2501\u2501\u2501\u2501\u2501\u2501\u2501\u2501\u2501\u2501\u2501\u2501\n\nBreakdown:\n\u2705 Content Quality: 100/100\n\u2705 ATS Compatibility: 100/100\n\u2705 Formatting: 95/100\n\u274c Impact Score: 30/100\n\n\u2501\u2501\u2501\u2501\u2501\u2501\u2501\u2501\u2501\u2501\u2501\u2501\u2501\u2501\u2501\u2501\u2501\u2501\u2501\u2501\u2501\u2501\u2501\u2501\u2501\u2501\u2501\u2501\u2501\u2501\u2501\u2501\u2501\u2501\u2501\u2501\n\n# \ud83d\udd25 RESUME ROAST SESSION \ud83d\udd25\n\n## **The Brutal Breakdown**\n\n### \ud83d\udcde **CONTACT INFO CATASTROPHE**\n*\"Congratulations! You've achieved the impossible - a resume that recruiters literally CAN'T call even if they wanted to!\"* \n\n**Why this kills your chances:** Recruiters are busy people who prefer quick phone calls over lengthy email chains. No phone number = you're basically playing hard-to-get in the worst possible way.\n\n**Fix it:** Add your phone number right under your name. Format: `(555) 123-4567` - revolutionary, I know! \ud83d\udcf1\n\n### \ud83d\udcdd **CONTENT QUALITY: The Overachiever's Paradox**\n*\"Perfect 100/100 on content but somehow still managed to forget basic human contact methods. It's like being a Michelin-star chef who forgets to turn on the stove!\"*\n\n**The issue:** Great content means nothing if people can't reach you to discuss it.\n\n### \ud83e\udd16 **ATS COMPATIBILITY: The Special Character Circus**\n*\"Your resume looks like it threw up emojis and fancy symbols - very artistic, completely unreadable to robots who actually matter.\"*\n\n**Why ATS systems hate you:** Those cute bullets (\u2022), fancy dashes (\u2014), and special characters turn into question marks or disappear entirely when parsed by Applicant Tracking Systems.\n\n**Fix it:** Stick to basic bullets (-), simple dashes (-), and standard characters. Save the fancy typography for your portfolio website! \n\n### \ud83d\udcca **IMPACT SCORE: 30/100 - THE PARTICIPATION TROPHY**\n*\"With an impact score of 30, your achievements hit about as hard as a wet paper towel in a pillow fight.\"*\n\n**The brutal truth:** You're probably listing job duties instead of actual accomplishments. \"Managed social media\" vs \"Increased Instagram engagement by 150% over 6 months, resulting in 300 new leads.\"\n\n**Fix it with examples:**\n- \u274c \"Responsible for customer service\"\n- \u2705 \"Resolved 95% of customer complaints within 24 hours, improving satisfaction scores from 3.2 to 4.7/5\"\n\n- \u274c \"Worked on marketing campaigns\" \n- \u2705 \"Led 3 digital campaigns that generated $50K in revenue and 25% increase in brand awareness\"\n\n### \ud83d\udcc5 **FORMATTING: The Time Traveler's Dilemma**\n*\"Your date formatting is more inconsistent than a weather forecast - pick a century and stick with it!\"*\n\n**Why consistency matters:** Inconsistent formatting screams \"I don't pay attention to details\" to hiring managers.\n\n**Fix it:** Choose ONE format and use it everywhere:\n- `Jan 2020 - Dec 2022` \u2705\n- `January 2020 - December 2022` \u2705\n- `01/2020 - 12/2022` \u2705\n- Mixing all three like a maniac \u274c\n\n---\n\n## \ud83d\udea8 **TOP 3 CRITICAL FIXES** \ud83d\udea8\n\n1. **ADD YOUR DAMN PHONE NUMBER** - This should take 30 seconds max\n2. **Quantify EVERYTHING** - Turn boring duties into impressive achievements with numbers\n3. **Fix those dates** - Pick a format, any format, just be consistent!\n\n---\n\n## \ud83c\udfc6 **Credit Where Credit's Due** \ud83c\udfc6\n\n**Genuine compliments (yes, really!):**\n- **LinkedIn inclusion** - Smart move! Shows you're digitally savvy \ud83d\udc54\n- **One-page format** - Perfect length, shows you can prioritize and communicate concisely \ud83d\udcc4\n- **Four relevant experiences** - Great career progression story \ud83d\udcc8\n- **ATS compatibility** - Once you ditch the special characters, you're golden \ud83e\udd16\u2705\n\n**Bottom line:** You're 90% there! These fixes will transform your resume from \"pretty good\" to \"impossible to ignore.\" Now stop reading this roast and go add that phone number! \ud83d\udcde\n\n*P.S. - That 88/100 overall score isn't bad at all. With these tweaks, you'll be pushing 95+. Now get back in there and crush it!* \ud83d\udcaa\n\n\u2501\u2501\u2501\u2501\u2501\u2501\u2501\u2501\u2501\u2501\u2501\u2501\u2501\u2501\u2501\u2501\u2501\u2501\u2501\u2501\u2501\u2501\u2501\u2501\u2501\u2501\u2501\u2501\u2501\u2501\u2501\u2501\u2501\u2501\u2501\u2501\n\n\ud83c\udfaf TOP 3 CRITICAL FIXES:\n1. Missing phone number: Add your phone number\n2. Inconsistent date formatting: Use consistent format like 'Jan 2020 - Dec 2022' throughout\n3. No professional summary or objective: Consider adding a brief 2-3 sentence summary highlighting your key qualifications\n\n\ud83d\udcaa WHAT YOU'RE DOING RIGHT:\n\u2022 Includes LinkedIn profile link\n\u2022 Concise one-page format (ideal for most professionals)\n\u2022 Shows 4 relevant work experiences\n",
  "score": 0,
  "issues": [
    {
      "category": "contact_info",
      "severity": "medium",
      "location": "contact",
      "problem": "Missing phone number",
      "fix": "Add your phone number"
    },
    {
      "category": "missing_section",
      "severity": "low",
      "location": "summary",
      "problem": "No professional summary or objective",
      "fix": "Consider adding a brief 2-3 sentence summary highlighting your key qualifications"
    },
    {
      "category": "consistency",
      "severity": "medium",
      "location": "formatting",
      "problem": "Inconsistent date formatting",
      "fix": "Use consistent format like 'Jan 2020 - Dec 2022' throughout"
    },
    {
      "category": "ats",
      "severity": "low",
      "location": "formatting",
      "problem": "Contains many special characters",
      "fix": "Minimize use of special characters that may confuse ATS"
    }
  ]
}